Digital_design/8-bit_arithmetic_logic_unit/ALU.vhdl
library ieee;
use ieee.std_logic_1164.all;
use ieee.std_logic_unsigned.all;
use ieee.numeric_std.all;

entity ALU is
	generic(constant N: natural := 1);
	port
	(
		A, B: in std_logic_vector(7 downto 0);
		ALU_Sel: in std_logic_vector(3 downto 0);
		ALU_Out: out std_logic_vector(7 downto 0);
		Carryout: out std_logic;
	);
end ALU;

architecture behavior of ALU is
	signal ALU_Result: std_logic_vector(7 downto 0);
	signal tmp: std_logic_vector(8 downto 0);
	
begin
	process (A,B,ALU_Sel)
	begin
		case(ALU_Sel)is
		when "0000" =>
			ALU_Result <= A + B;
		when "0001" =>
			ALU_Result <= A - B;
		when "0010" =>
			ALU_Result <= std_logic_vector(to_unsigned((to_integer(unsigned(A)) * to_integer(unsigned(B))),8));
		when "0011" =>
			ALU_Result <= std_logic_vector(to_unsigned((to_integer(unsigned(A)) / to_integer(unsigned(B))),8));
		when "0100" =>
			ALU_Result <= std_logic_vector(unsigned(A) sll N);
		when "0101" =>
			ALU_Result <= std_logic_vector(unsigned(A) srl N);
		when "0110" =>
			ALU_Result <= std_logic_vector(unsigned(A) rol N);
		when "0111" =>
			ALU_Result <= std_logic_vector(unsigned(A) ror N);
		when "1000" =>
			ALU_Result <= A and B;
		when "1001" =>
			ALU_Result <= A or B;
		when "1010" =>
			ALU_Result <= A xor B;
		when "1011" =>
			ALU_Result <= A nor B;
		when "1100" =>
			ALU_Result <= A nand B;
		when "1101" =>
			ALU_Result <= A xnor B;
		when "1110" =>
			if (A > B) then
				ALU_Result <= x"01";
			else
				ALU_Result <= x"00";
			end if;
			
		when "1111" =>
			if (A = B) then
				ALU_Result <= x"01";
			else
				ALU_Result <= x"00";
			end if;
		
		when others =>
			ALU_Result <= A + B;
	
		end case;
	end  process
	
	ALU_Out <= ALU_Result;
	tmp <= ('0'&A) + ('0'&B);
	Carryout <= tmp(8); --Carry flag
	
end behavior;

Digital_design/8-bit_arithmetic_logic_unit/ALU_tb.vhdl
library ieee;
use ieee.std_logic_1164.all;
--use ieee.std_logic_unsigned.all;
use ieee.numeric_std.all;

entity ALU_tb is
end ALU_tb;

architecture behavior of ALU_tb is
	component ALU
		port
		(
			A, B: in std_logic_vector(7 downto 0);
			ALU_Sel: in std_logic_vector(3 downto 0);
			ALU_Out: out std_logic_vector(7 downto 0);
			Carryout: out std_logic
		);
	end component;
	
	signal A, B: std_logic_vector(7 downto 0);
	signal ALU_Sel: std_logic_vector(3 downto 0);
	signal C: std_logic_vector(3 downto 0);
	signal ALU_Out: std_logic_vector(7 downto 0);
	signal Carryout: std_logic; 

begin
	Arithmetic_Logical_Unit: ALU port map(A => A, B => B, ALU_Sel => ALU_Sel, ALU_Out => ALU_Out, Carryout => Carryout);
	process begin
		C <= "0001";
		A <= x"0A";
		B <= x"02";
		ALU_Sel <= x"0";
		wait for 1 ns;
		
		
		for i in 0 to 15 loop
			ALU_Sel <= std_logic_vector(to_unsigned((to_integer(unsigned(ALU_Sel)) + to_integer(unsigned(C))),4));
			wait for 1 ns;
		end loop;
		
		A <= x"F6";
		B <= x"0A";
		
		wait;
	end process;
end behavior;

Digital_design/8-bit_arithmetic_logic_unit/ALU.vcd
$date
  Thu Sep 21 01:46:42 2023
$end
$version
  GHDL v0
$end
$timescale
  1 fs
$end
$scope module standard $end
$upscope $end
$scope module std_logic_1164 $end
$upscope $end
$scope module numeric_std $end
$upscope $end
$scope module alu_tb $end
$var reg 8 ! a[7:0] $end
$var reg 8 " b[7:0] $end
$var reg 4 # alu_sel[3:0] $end
$var reg 4 $ c[3:0] $end
$var reg 8 % alu_out[7:0] $end
$var reg 1 & carryout $end
$scope module arithmetic_logical_unit $end
$var reg 8 ' a[7:0] $end
$var reg 8 ( b[7:0] $end
$var reg 4 ) alu_sel[3:0] $end
$var reg 8 * alu_out[7:0] $end
$var reg 1 + carryout $end
$var reg 8 , alu_result[7:0] $end
$var reg 9 - tmp[8:0] $end
$upscope $end
$upscope $end
$enddefinitions $end
#0
b00001010 !
b00000010 "
b0000 #
b0001 $
b00001100 %
U&
b00001010 '
b00000010 (
b0000 )
b00001100 *
U+
b00001100 ,
bUUUUUUUUU -
#1000000
b0001 #
b00001000 %
b0001 )
b00001000 *
b00001000 ,
#2000000
b0010 #
b00010100 %
b0010 )
b00010100 *
b00010100 ,
#3000000
b0011 #
b00000101 %
b0011 )
b00000101 *
b00000101 ,
#4000000
b0100 #
b00010100 %
b0100 )
b00010100 *
b00010100 ,
#5000000
b0101 #
b00000101 %
b0101 )
b00000101 *
b00000101 ,
#6000000
b0110 #
b00010100 %
b0110 )
b00010100 *
b00010100 ,
#7000000
b0111 #
b00000101 %
b0111 )
b00000101 *
b00000101 ,
#8000000
b1000 #
b00000010 %
b1000 )
b00000010 *
b00000010 ,
#9000000
b1001 #
b00001010 %
b1001 )
b00001010 *
b00001010 ,
#10000000
b1010 #
b00001000 %
b1010 )
b00001000 *
b00001000 ,
#11000000
b1011 #
b11110101 %
b1011 )
b11110101 *
b11110101 ,
#12000000
b1100 #
b11111101 %
b1100 )
b11111101 *
b11111101 ,
#13000000
b1101 #
b11110111 %
b1101 )
b11110111 *
b11110111 ,
#14000000
b1110 #
b00000001 %
b1110 )
b00000001 *
b00000001 ,
#15000000
b1111 #
b00000000 %
b1111 )
b00000000 *
b00000000 ,
#16000000
b0000 #
b00001100 %
b0000 )
b00001100 *
b00001100 ,
#17000000
b11110110 !
b00001010 "
b00000000 %
b11110110 '
b00001010 (
b00000000 *
b00000000 ,
